ogimg/__init__.py
ogimg/cli.py
ogimg-0.1.2.dist-info/entry_points.txt
ogimg-0.1.2.dist-info/WHEEL
ogimg-0.1.2.dist-info/METADATA
ogimg-0.1.2.dist-info/license_files/LICENSE
ogimg-0.1.2.dist-info/RECORD
