Metadata-Version: 2.1
Name: ogimg
Version: 0.1.2
Summary: A Python CLI for downloading metadata images (e.g., OG images) from web pages.
License: MIT
Author-email: João Palmeiro <joaopalmeiro@proton.me>
Requires-Python: >=3.7
Requires-Dist: click>=8.1.3
Requires-Dist: metadata-parser>=0.10.5
Project-URL: Homepage, https://github.com/joaopalmeiro/ogimg
Project-URL: Repository, https://github.com/joaopalmeiro/ogimg
